setup.cfg
setup.py
lazy_record/__init__.py
lazy_record/associations.py
lazy_record/errors.py
lazy_record/query.py
lazy_record/repo.py
lazy_record/typecasts.py
lazy_record/validations.py
lazy_record.egg-info/PKG-INFO
lazy_record.egg-info/SOURCES.txt
lazy_record.egg-info/dependency_links.txt
lazy_record.egg-info/requires.txt
lazy_record.egg-info/top_level.txt
lazy_record/base/__init__.py
lazy_record/base/validations.py
test/test_associations.py
test/test_base.py
test/test_query.py
test/test_related_records.py
test/test_repo.py
test/test_scopes.py
test/test_typecasts.py
test/test_validations.py