Metadata-Version: 1.1
Name: lazy-record
Version: 0.5.2
Summary: Generic Model Layer for Python Web Applications using Sqlite3
Home-page: https://github.com/ECESeniorDesign/lazy_record
Author: Chase Conklin
Author-email: cconkli4@u.rochester.edu
License: UNKNOWN
Download-URL: https://github.com/ECESeniorDesign/lazy_record/tarball/0.5.2
Keywords: flask
Platform: UNKNOWN
